{ "traceEvents":[{}
,{"args":{"name":"CPU HIP API"},"ph":"M","pid":2,"name":"process_name","sort_index":0}
,{"args":{"name":"COPY"},"ph":"M","pid":1,"name":"process_name","sort_index":1}
,{"args":{"name":"GPU0"},"ph":"M","pid":6,"name":"process_name","sort_index":2}
,{"args":{"name":"GPU Barriers0"},"ph":"M","pid":518,"name":"process_name","sort_index":3}
,{"args":{"name":"GPU1"},"ph":"M","pid":7,"name":"process_name","sort_index":4}
,{"args":{"name":"GPU Barriers1"},"ph":"M","pid":519,"name":"process_name","sort_index":5}
,{"args":{"name":"GPU2"},"ph":"M","pid":8,"name":"process_name","sort_index":6}
,{"args":{"name":"GPU Barriers2"},"ph":"M","pid":520,"name":"process_name","sort_index":7}
,{"args":{"name":"GPU3"},"ph":"M","pid":9,"name":"process_name","sort_index":8}
,{"args":{"name":"GPU Barriers3"},"ph":"M","pid":521,"name":"process_name","sort_index":9}
,{"args":{"name":"GPU4"},"ph":"M","pid":10,"name":"process_name","sort_index":10}
,{"args":{"name":"GPU Barriers4"},"ph":"M","pid":522,"name":"process_name","sort_index":11}
,{"args":{"name":"GPU5"},"ph":"M","pid":11,"name":"process_name","sort_index":12}
,{"args":{"name":"GPU Barriers5"},"ph":"M","pid":523,"name":"process_name","sort_index":13}
,{"args":{"name":"GPU6"},"ph":"M","pid":12,"name":"process_name","sort_index":14}
,{"args":{"name":"GPU Barriers6"},"ph":"M","pid":524,"name":"process_name","sort_index":15}
,{"args":{"name":"GPU7"},"ph":"M","pid":13,"name":"process_name","sort_index":16}
,{"args":{"name":"GPU Barriers7"},"ph":"M","pid":525,"name":"process_name","sort_index":17}
,{"args":{"name":"GPU8"},"ph":"M","pid":14,"name":"process_name","sort_index":18}
,{"args":{"name":"GPU Barriers8"},"ph":"M","pid":526,"name":"process_name","sort_index":19}
,{"ph":"X","name":"CopyDeviceToDevice","pid":1,"tid":0,"ts":"506201251869","dur":"8",
  "args":{
    "BeginNs":"506201251869424",
    "EndNs":"506201251877584",
    "dev-id":"8",
    "queue-id":"0",
    "Name":"CopyDeviceToDevice",
    "pid":"1136109",
    "tid":"1136109",
    "stream-id":"0",
    "Data":"",
    "DurationNs":"8160"
  }
}
,{"ph":"X","name":"CopyDeviceToDevice","pid":1,"tid":0,"ts":"506201253170","dur":"6",
  "args":{
    "BeginNs":"506201253170547",
    "EndNs":"506201253177107",
    "dev-id":"8",
    "queue-id":"0",
    "Name":"CopyDeviceToDevice",
    "pid":"1136109",
    "tid":"1136109",
    "stream-id":"0",
    "Data":"",
    "DurationNs":"6560"
  }
}
,{"ph":"X","name":"hipMalloc","pid":2,"tid":1136109,"ts":"506200915768","dur":"53",
  "args":{
    "BeginNs":"506200915768246",
    "EndNs":"506200915822225",
    "pid":"1136109",
    "tid":"1136109",
    "Name":"hipMalloc",
    "args":"( ptr(0x7f54a4400000) size(4))",
    "Data":"",
    "DurationNs":"53979"
  }
}
,{"ph":"X","name":"hipMalloc","pid":2,"tid":1136109,"ts":"506200915833","dur":"3",
  "args":{
    "BeginNs":"506200915833635",
    "EndNs":"506200915837235",
    "pid":"1136109",
    "tid":"1136109",
    "Name":"hipMalloc",
    "args":"( ptr(0x7f54a4401000) size(4))",
    "Data":"",
    "DurationNs":"3600"
  }
}
,{"ph":"X","name":"hipHostRegister","pid":2,"tid":1136109,"ts":"506200915840","dur":"1315",
  "args":{
    "BeginNs":"506200915840285",
    "EndNs":"506200917156061",
    "pid":"1136109",
    "tid":"1136109",
    "Name":"hipHostRegister",
    "args":"( hostPtr(0x3e87bc60) sizeBytes(4) flags(0))",
    "Data":"",
    "DurationNs":"1315776"
  }
}
,{"ph":"X","name":"hipHostRegister","pid":2,"tid":1136109,"ts":"506200917160","dur":"96",
  "args":{
    "BeginNs":"506200917160150",
    "EndNs":"506200917256489",
    "pid":"1136109",
    "tid":"1136109",
    "Name":"hipHostRegister",
    "args":"( hostPtr(0x3e87bc80) sizeBytes(4) flags(0))",
    "Data":"",
    "DurationNs":"96339"
  }
}
,{"ph":"X","name":"hipMemcpy","pid":2,"tid":1136109,"ts":"506200917260","dur":"334625",
  "args":{
    "BeginNs":"506200917260769",
    "EndNs":"506201251886715",
    "pid":"1136109",
    "tid":"1136109",
    "Name":"hipMemcpy",
    "args":"( dst(0x7f54a4400000) src(0x3e87bc60) sizeBytes(4) kind(1))",
    "Data":"",
    "DurationNs":"334625946"
  }
}
,{"ph":"X","name":"hipMalloc","pid":2,"tid":1136109,"ts":"506201251896","dur":"12",
  "args":{
    "BeginNs":"506201251896945",
    "EndNs":"506201251909045",
    "pid":"1136109",
    "tid":"1136109",
    "Name":"hipMalloc",
    "args":"( ptr(0x7f54a4402000) size(4))",
    "Data":"",
    "DurationNs":"12100"
  }
}
,{"ph":"X","name":"hipMalloc","pid":2,"tid":1136109,"ts":"506201251911","dur":"1",
  "args":{
    "BeginNs":"506201251911985",
    "EndNs":"506201251913805",
    "pid":"1136109",
    "tid":"1136109",
    "Name":"hipMalloc",
    "args":"( ptr(0x7f54a4403000) size(8))",
    "Data":"",
    "DurationNs":"1820"
  }
}
,{"ph":"X","name":"__hipPushCallConfiguration","pid":2,"tid":1136109,"ts":"506201251919","dur":"1",
  "args":{
    "BeginNs":"506201251919355",
    "EndNs":"506201251920065",
    "pid":"1136109",
    "tid":"1136109",
    "Name":"__hipPushCallConfiguration",
    "args":"( gridDim({z(1) y(1) x(1}) blockDim({z(1) y(1) x(256}) sharedMem(48) stream(1))",
    "Data":"",
    "DurationNs":"710"
  }
}
,{"ph":"X","name":"__hipPopCallConfiguration","pid":2,"tid":1136109,"ts":"506201251922","dur":"1",
  "args":{
    "BeginNs":"506201251922755",
    "EndNs":"506201251923195",
    "pid":"1136109",
    "tid":"1136109",
    "Name":"__hipPopCallConfiguration",
    "args":"( gridDim({z(1) y(1) x(1}) blockDim({z(1) y(1) x(256}) sharedMem(48) stream(1))",
    "Data":"",
    "DurationNs":"440"
  }
}
,{"ph":"X","name":"hipLaunchKernel","pid":2,"tid":1136109,"ts":"506201251927","dur":"1177",
  "args":{
    "BeginNs":"506201251927915",
    "EndNs":"506201253105172",
    "pid":"1136109",
    "tid":"1136109",
    "Name":"hipLaunchKernel",
    "args":"( kernel(onlinePartialKernel) function_address(0x201648) numBlocks({z(1) y(1) x(1}) dimBlocks({z(1) y(1) x(256}) args(0x7ffd3d081270) sharedMemBytes(48) stream(1))",
    "Data":"",
    "DurationNs":"1177257"
  }
}
,{"ph":"X","name":"hipGetLastError","pid":2,"tid":1136109,"ts":"506201253123","dur":"1",
  "args":{
    "BeginNs":"506201253123952",
    "EndNs":"506201253124142",
    "pid":"1136109",
    "tid":"1136109",
    "Name":"hipGetLastError",
    "args":"( ))",
    "Data":"",
    "DurationNs":"190"
  }
}
,{"ph":"X","name":"hipMalloc","pid":2,"tid":1136109,"ts":"506201253127","dur":"3",
  "args":{
    "BeginNs":"506201253127162",
    "EndNs":"506201253130791",
    "pid":"1136109",
    "tid":"1136109",
    "Name":"hipMalloc",
    "args":"( ptr(0x7f54a4404000) size(4))",
    "Data":"",
    "DurationNs":"3629"
  }
}
,{"ph":"X","name":"hipMalloc","pid":2,"tid":1136109,"ts":"506201253131","dur":"1",
  "args":{
    "BeginNs":"506201253131171",
    "EndNs":"506201253132571",
    "pid":"1136109",
    "tid":"1136109",
    "Name":"hipMalloc",
    "args":"( ptr(0x7f54a4405000) size(8))",
    "Data":"",
    "DurationNs":"1400"
  }
}
,{"ph":"X","name":"__hipPushCallConfiguration","pid":2,"tid":1136109,"ts":"506201253135","dur":"1",
  "args":{
    "BeginNs":"506201253135011",
    "EndNs":"506201253135262",
    "pid":"1136109",
    "tid":"1136109",
    "Name":"__hipPushCallConfiguration",
    "args":"( gridDim({z(1) y(1) x(1}) blockDim({z(1) y(1) x(256}) sharedMem(48) stream(1))",
    "Data":"",
    "DurationNs":"251"
  }
}
,{"ph":"X","name":"__hipPopCallConfiguration","pid":2,"tid":1136109,"ts":"506201253135","dur":"1",
  "args":{
    "BeginNs":"506201253135722",
    "EndNs":"506201253136022",
    "pid":"1136109",
    "tid":"1136109",
    "Name":"__hipPopCallConfiguration",
    "args":"( gridDim({z(1) y(1) x(1}) blockDim({z(1) y(1) x(256}) sharedMem(48) stream(1))",
    "Data":"",
    "DurationNs":"300"
  }
}
,{"ph":"X","name":"hipLaunchKernel","pid":2,"tid":1136109,"ts":"506201253136","dur":"3",
  "args":{
    "BeginNs":"506201253136462",
    "EndNs":"506201253140422",
    "pid":"1136109",
    "tid":"1136109",
    "Name":"hipLaunchKernel",
    "args":"( kernel(onlineFinalReduceKernel) function_address(0x201650) numBlocks({z(1) y(1) x(1}) dimBlocks({z(1) y(1) x(256}) args(0x7ffd3d081270) sharedMemBytes(48) stream(1))",
    "Data":"",
    "DurationNs":"3960"
  }
}
,{"ph":"X","name":"hipGetLastError","pid":2,"tid":1136109,"ts":"506201253142","dur":"1",
  "args":{
    "BeginNs":"506201253142191",
    "EndNs":"506201253142291",
    "pid":"1136109",
    "tid":"1136109",
    "Name":"hipGetLastError",
    "args":"( ))",
    "Data":"",
    "DurationNs":"100"
  }
}
,{"ph":"X","name":"__hipPushCallConfiguration","pid":2,"tid":1136109,"ts":"506201253142","dur":"1",
  "args":{
    "BeginNs":"506201253142662",
    "EndNs":"506201253142811",
    "pid":"1136109",
    "tid":"1136109",
    "Name":"__hipPushCallConfiguration",
    "args":"( gridDim({z(1) y(1) x(1}) blockDim({z(1) y(1) x(256}) sharedMem(0) stream(1))",
    "Data":"",
    "DurationNs":"149"
  }
}
,{"ph":"X","name":"__hipPopCallConfiguration","pid":2,"tid":1136109,"ts":"506201253143","dur":"1",
  "args":{
    "BeginNs":"506201253143111",
    "EndNs":"506201253143282",
    "pid":"1136109",
    "tid":"1136109",
    "Name":"__hipPopCallConfiguration",
    "args":"( gridDim({z(1) y(1) x(1}) blockDim({z(1) y(1) x(256}) sharedMem(0) stream(1))",
    "Data":"",
    "DurationNs":"171"
  }
}
,{"ph":"X","name":"hipLaunchKernel","pid":2,"tid":1136109,"ts":"506201253144","dur":"3",
  "args":{
    "BeginNs":"506201253144531",
    "EndNs":"506201253147611",
    "pid":"1136109",
    "tid":"1136109",
    "Name":"hipLaunchKernel",
    "args":"( kernel(softmaxWriteKernel) function_address(0x201658) numBlocks({z(1) y(1) x(1}) dimBlocks({z(1) y(1) x(256}) args(0x7ffd3d081270) sharedMemBytes(0) stream(1))",
    "Data":"",
    "DurationNs":"3080"
  }
}
,{"ph":"X","name":"hipGetLastError","pid":2,"tid":1136109,"ts":"506201253148","dur":"1",
  "args":{
    "BeginNs":"506201253148191",
    "EndNs":"506201253148282",
    "pid":"1136109",
    "tid":"1136109",
    "Name":"hipGetLastError",
    "args":"( ))",
    "Data":"",
    "DurationNs":"91"
  }
}
,{"ph":"X","name":"hipMemcpy","pid":2,"tid":1136109,"ts":"506201253150","dur":"34",
  "args":{
    "BeginNs":"506201253150042",
    "EndNs":"506201253184101",
    "pid":"1136109",
    "tid":"1136109",
    "Name":"hipMemcpy",
    "args":"( dst(0x3e87bc80) src(0x7f54a4401000) sizeBytes(4) kind(2))",
    "Data":"",
    "DurationNs":"34059"
  }
}
,{"ph":"X","name":"hipFree","pid":2,"tid":1136109,"ts":"506201253188","dur":"60",
  "args":{
    "BeginNs":"506201253188411",
    "EndNs":"506201253249180",
    "pid":"1136109",
    "tid":"1136109",
    "Name":"hipFree",
    "args":"( ptr(0x7f54a4400000))",
    "Data":"",
    "DurationNs":"60769"
  }
}
,{"ph":"X","name":"hipFree","pid":2,"tid":1136109,"ts":"506201253249","dur":"1",
  "args":{
    "BeginNs":"506201253249890",
    "EndNs":"506201253251710",
    "pid":"1136109",
    "tid":"1136109",
    "Name":"hipFree",
    "args":"( ptr(0x7f54a4401000))",
    "Data":"",
    "DurationNs":"1820"
  }
}
,{"ph":"X","name":"hipFree","pid":2,"tid":1136109,"ts":"506201253253","dur":"1",
  "args":{
    "BeginNs":"506201253253640",
    "EndNs":"506201253255500",
    "pid":"1136109",
    "tid":"1136109",
    "Name":"hipFree",
    "args":"( ptr(0x7f54a4402000))",
    "Data":"",
    "DurationNs":"1860"
  }
}
,{"ph":"X","name":"hipFree","pid":2,"tid":1136109,"ts":"506201253255","dur":"1",
  "args":{
    "BeginNs":"506201253255890",
    "EndNs":"506201253257420",
    "pid":"1136109",
    "tid":"1136109",
    "Name":"hipFree",
    "args":"( ptr(0x7f54a4403000))",
    "Data":"",
    "DurationNs":"1530"
  }
}
,{"ph":"X","name":"hipFree","pid":2,"tid":1136109,"ts":"506201253258","dur":"1",
  "args":{
    "BeginNs":"506201253258820",
    "EndNs":"506201253260500",
    "pid":"1136109",
    "tid":"1136109",
    "Name":"hipFree",
    "args":"( ptr(0x7f54a4404000))",
    "Data":"",
    "DurationNs":"1680"
  }
}
,{"ph":"X","name":"hipFree","pid":2,"tid":1136109,"ts":"506201253260","dur":"1",
  "args":{
    "BeginNs":"506201253260800",
    "EndNs":"506201253262740",
    "pid":"1136109",
    "tid":"1136109",
    "Name":"hipFree",
    "args":"( ptr(0x7f54a4405000))",
    "Data":"",
    "DurationNs":"1940"
  }
}
,{"ph":"X","name":"hipHostUnregister","pid":2,"tid":1136109,"ts":"506201253264","dur":"6",
  "args":{
    "BeginNs":"506201253264070",
    "EndNs":"506201253270850",
    "pid":"1136109",
    "tid":"1136109",
    "Name":"hipHostUnregister",
    "args":"( hostPtr(0x3e87bc60))",
    "Data":"",
    "DurationNs":"6780"
  }
}
,{"ph":"X","name":"hipHostUnregister","pid":2,"tid":1136109,"ts":"506201253272","dur":"2",
  "args":{
    "BeginNs":"506201253272350",
    "EndNs":"506201253274450",
    "pid":"1136109",
    "tid":"1136109",
    "Name":"hipHostUnregister",
    "args":"( hostPtr(0x3e87bc80))",
    "Data":"",
    "DurationNs":"2100"
  }
}
,{"ph":"X","name":"onlinePartialKernel","pid":14,"tid":1,"ts":"506201253112","dur":"26",
  "args":{
    "BeginNs":"506201253112627",
    "EndNs":"506201253139027",
    "dev-id":"8",
    "queue-id":"0",
    "Name":"onlinePartialKernel",
    "pid":"1136109",
    "tid":"1136109",
    "stream-id":"1",
    "Data":"",
    "DurationNs":"26400"
  }
}
,{"ph":"X","name":"onlineFinalReduceKernel","pid":14,"tid":1,"ts":"506201253144","dur":"21",
  "args":{
    "BeginNs":"506201253144467",
    "EndNs":"506201253166227",
    "dev-id":"8",
    "queue-id":"0",
    "Name":"onlineFinalReduceKernel",
    "pid":"1136109",
    "tid":"1136109",
    "stream-id":"1",
    "Data":"",
    "DurationNs":"21760"
  }
}
,{"ph":"X","name":"softmaxWriteKernel","pid":14,"tid":1,"ts":"506201253166","dur":"4",
  "args":{
    "BeginNs":"506201253166227",
    "EndNs":"506201253170547",
    "dev-id":"8",
    "queue-id":"0",
    "Name":"softmaxWriteKernel",
    "pid":"1136109",
    "tid":"1136109",
    "stream-id":"1",
    "Data":"",
    "DurationNs":"4320"
  }
}
,{"ts":506201084572,"ph":"s","cat":"DataFlow","id":0,"pid":2,"tid":1136109,"name":"dep"}
,{"ts":506201251869,"ph":"t","cat":"DataFlow","id":0,"pid":1,"tid":0,"name":"dep"}
,{"ts":506201253167,"ph":"s","cat":"DataFlow","id":1,"pid":2,"tid":1136109,"name":"dep"}
,{"ts":506201253170,"ph":"t","cat":"DataFlow","id":1,"pid":1,"tid":0,"name":"dep"}
,{"ts":506201252515,"ph":"s","cat":"DataFlow","id":5,"pid":2,"tid":1136109,"name":"dep"}
,{"ts":506201253112,"ph":"t","cat":"DataFlow","id":5,"pid":14,"tid":1,"name":"dep"}
,{"ts":506201253137,"ph":"s","cat":"DataFlow","id":6,"pid":2,"tid":1136109,"name":"dep"}
,{"ts":506201253144,"ph":"t","cat":"DataFlow","id":6,"pid":14,"tid":1,"name":"dep"}
,{"ts":506201253145,"ph":"s","cat":"DataFlow","id":7,"pid":2,"tid":1136109,"name":"dep"}
,{"ts":506201253166,"ph":"t","cat":"DataFlow","id":7,"pid":14,"tid":1,"name":"dep"}
],
"otherData": {
    "CMD": "rocminfo",
    "HSASystemAttributes.RuntimeVersion": "1.15",
    "HSASystemAttributes.RuntimeExtVersion": "1.7",
    "HSASystemAttributes.SystemTimestampFreq.": "1000.000000MHz",
    "HSASystemAttributes.Sig.MaxWaitDuration": "18446744073709551615(0xFFFFFFFFFFFFFFFF)(timestampcount)",
    "HSASystemAttributes.MachineModel": "LARGE",
    "HSASystemAttributes.SystemEndianness": "LITTLE",
    "HSASystemAttributes.Mwaitx": "DISABLED",
    "HSASystemAttributes.XNACKenabled": "NO",
    "HSASystemAttributes.DMAbufSupport": "NO",
    "HSASystemAttributes.VMMSupport": "NO",
    "Agent1.Name": "AMDEPYC774264-CoreProcessor",
    "Agent1.Uuid": "CPU-XX",
    "Agent1.MarketingName": "AMDEPYC774264-CoreProcessor",
    "Agent1.VendorName": "CPU",
    "Agent1.Feature": "Nonespecified",
    "Agent1.Profile": "FULL_PROFILE",
    "Agent1.FloatRoundMode": "NEAR",
    "Agent1.MaxQueueNumber": "0(0x0)",
    "Agent1.QueueMinSize": "0(0x0)",
    "Agent1.QueueMaxSize": "0(0x0)",
    "Agent1.QueueType": "MULTI",
    "Agent1.Node": "0",
    "Agent1.DeviceType": "CPU",
    "Agent1.CacheInfo.L1": "32768(0x8000)KB",
    "Agent1.ChipID": "0(0x0)",
    "Agent1.ASICRevision": "0(0x0)",
    "Agent1.CachelineSize": "64(0x40)",
    "Agent1.MaxClockFreq.(MHz)": "2250",
    "Agent1.BDFID": "0",
    "Agent1.InternalNodeID": "0",
    "Agent1.ComputeUnit": "16",
    "Agent1.SIMDsperCU": "0",
    "Agent1.ShaderEngines": "0",
    "Agent1.ShaderArrs.perEng.": "0",
    "Agent1.WatchPtsonAddr.Ranges": "1",
    "Agent1.MemoryProperties.Features": "None",
    "Agent1.MemoryProperties.PoolInfo.Pool1.Segment": "GLOBAL",
    "Agent1.MemoryProperties.PoolInfo.Pool1.FLAGS": "FINEGRAINED",
    "Agent1.MemoryProperties.PoolInfo.Pool1.Size": "65858416(0x3eceb70)KB",
    "Agent1.MemoryProperties.PoolInfo.Pool1.Allocatable": "TRUE",
    "Agent1.MemoryProperties.PoolInfo.Pool1.AllocGranule": "4KB",
    "Agent1.MemoryProperties.PoolInfo.Pool1.AllocRecommendedGranule": "4KB",
    "Agent1.MemoryProperties.PoolInfo.Pool1.AllocAlignment": "4KB",
    "Agent1.MemoryProperties.PoolInfo.Pool1.Accessiblebyall": "TRUE",
    "Agent1.MemoryProperties.PoolInfo.Pool2.Segment": "GLOBAL",
    "Agent1.MemoryProperties.PoolInfo.Pool2.FLAGS": "EXTENDEDFINEGRAINED",
    "Agent1.MemoryProperties.PoolInfo.Pool2.Size": "65858416(0x3eceb70)KB",
    "Agent1.MemoryProperties.PoolInfo.Pool2.Allocatable": "TRUE",
    "Agent1.MemoryProperties.PoolInfo.Pool2.AllocGranule": "4KB",
    "Agent1.MemoryProperties.PoolInfo.Pool2.AllocRecommendedGranule": "4KB",
    "Agent1.MemoryProperties.PoolInfo.Pool2.AllocAlignment": "4KB",
    "Agent1.MemoryProperties.PoolInfo.Pool2.Accessiblebyall": "TRUE",
    "Agent1.MemoryProperties.PoolInfo.Pool3.Segment": "GLOBAL",
    "Agent1.MemoryProperties.PoolInfo.Pool3.FLAGS": "KERNARG,FINEGRAINED",
    "Agent1.MemoryProperties.PoolInfo.Pool3.Size": "65858416(0x3eceb70)KB",
    "Agent1.MemoryProperties.PoolInfo.Pool3.Allocatable": "TRUE",
    "Agent1.MemoryProperties.PoolInfo.Pool3.AllocGranule": "4KB",
    "Agent1.MemoryProperties.PoolInfo.Pool3.AllocRecommendedGranule": "4KB",
    "Agent1.MemoryProperties.PoolInfo.Pool3.AllocAlignment": "4KB",
    "Agent1.MemoryProperties.PoolInfo.Pool3.Accessiblebyall": "TRUE",
    "Agent1.MemoryProperties.PoolInfo.Pool4.Segment": "GLOBAL",
    "Agent1.MemoryProperties.PoolInfo.Pool4.FLAGS": "COARSEGRAINED",
    "Agent1.MemoryProperties.PoolInfo.Pool4.Size": "65858416(0x3eceb70)KB",
    "Agent1.MemoryProperties.PoolInfo.Pool4.Allocatable": "TRUE",
    "Agent1.MemoryProperties.PoolInfo.Pool4.AllocGranule": "4KB",
    "Agent1.MemoryProperties.PoolInfo.Pool4.AllocRecommendedGranule": "4KB",
    "Agent1.MemoryProperties.PoolInfo.Pool4.AllocAlignment": "4KB",
    "Agent1.MemoryProperties.PoolInfo.Pool4.Accessiblebyall": "TRUE",
    "Agent2.Name": "AMDEPYC774264-CoreProcessor",
    "Agent2.Uuid": "CPU-XX",
    "Agent2.MarketingName": "AMDEPYC774264-CoreProcessor",
    "Agent2.VendorName": "CPU",
    "Agent2.Feature": "Nonespecified",
    "Agent2.Profile": "FULL_PROFILE",
    "Agent2.FloatRoundMode": "NEAR",
    "Agent2.MaxQueueNumber": "0(0x0)",
    "Agent2.QueueMinSize": "0(0x0)",
    "Agent2.QueueMaxSize": "0(0x0)",
    "Agent2.QueueType": "MULTI",
    "Agent2.Node": "1",
    "Agent2.DeviceType": "CPU",
    "Agent2.CacheInfo.L1": "32768(0x8000)KB",
    "Agent2.ChipID": "0(0x0)",
    "Agent2.ASICRevision": "0(0x0)",
    "Agent2.CachelineSize": "64(0x40)",
    "Agent2.MaxClockFreq.(MHz)": "2250",
    "Agent2.BDFID": "0",
    "Agent2.InternalNodeID": "1",
    "Agent2.ComputeUnit": "16",
    "Agent2.SIMDsperCU": "0",
    "Agent2.ShaderEngines": "0",
    "Agent2.ShaderArrs.perEng.": "0",
    "Agent2.WatchPtsonAddr.Ranges": "1",
    "Agent2.MemoryProperties.Features": "None",
    "Agent2.MemoryProperties.PoolInfo.Pool1.Segment": "GLOBAL",
    "Agent2.MemoryProperties.PoolInfo.Pool1.FLAGS": "FINEGRAINED",
    "Agent2.MemoryProperties.PoolInfo.Pool1.Size": "66055088(0x3efebb0)KB",
    "Agent2.MemoryProperties.PoolInfo.Pool1.Allocatable": "TRUE",
    "Agent2.MemoryProperties.PoolInfo.Pool1.AllocGranule": "4KB",
    "Agent2.MemoryProperties.PoolInfo.Pool1.AllocRecommendedGranule": "4KB",
    "Agent2.MemoryProperties.PoolInfo.Pool1.AllocAlignment": "4KB",
    "Agent2.MemoryProperties.PoolInfo.Pool1.Accessiblebyall": "TRUE",
    "Agent2.MemoryProperties.PoolInfo.Pool2.Segment": "GLOBAL",
    "Agent2.MemoryProperties.PoolInfo.Pool2.FLAGS": "EXTENDEDFINEGRAINED",
    "Agent2.MemoryProperties.PoolInfo.Pool2.Size": "66055088(0x3efebb0)KB",
    "Agent2.MemoryProperties.PoolInfo.Pool2.Allocatable": "TRUE",
    "Agent2.MemoryProperties.PoolInfo.Pool2.AllocGranule": "4KB",
    "Agent2.MemoryProperties.PoolInfo.Pool2.AllocRecommendedGranule": "4KB",
    "Agent2.MemoryProperties.PoolInfo.Pool2.AllocAlignment": "4KB",
    "Agent2.MemoryProperties.PoolInfo.Pool2.Accessiblebyall": "TRUE",
    "Agent2.MemoryProperties.PoolInfo.Pool3.Segment": "GLOBAL",
    "Agent2.MemoryProperties.PoolInfo.Pool3.FLAGS": "KERNARG,FINEGRAINED",
    "Agent2.MemoryProperties.PoolInfo.Pool3.Size": "66055088(0x3efebb0)KB",
    "Agent2.MemoryProperties.PoolInfo.Pool3.Allocatable": "TRUE",
    "Agent2.MemoryProperties.PoolInfo.Pool3.AllocGranule": "4KB",
    "Agent2.MemoryProperties.PoolInfo.Pool3.AllocRecommendedGranule": "4KB",
    "Agent2.MemoryProperties.PoolInfo.Pool3.AllocAlignment": "4KB",
    "Agent2.MemoryProperties.PoolInfo.Pool3.Accessiblebyall": "TRUE",
    "Agent2.MemoryProperties.PoolInfo.Pool4.Segment": "GLOBAL",
    "Agent2.MemoryProperties.PoolInfo.Pool4.FLAGS": "COARSEGRAINED",
    "Agent2.MemoryProperties.PoolInfo.Pool4.Size": "66055088(0x3efebb0)KB",
    "Agent2.MemoryProperties.PoolInfo.Pool4.Allocatable": "TRUE",
    "Agent2.MemoryProperties.PoolInfo.Pool4.AllocGranule": "4KB",
    "Agent2.MemoryProperties.PoolInfo.Pool4.AllocRecommendedGranule": "4KB",
    "Agent2.MemoryProperties.PoolInfo.Pool4.AllocAlignment": "4KB",
    "Agent2.MemoryProperties.PoolInfo.Pool4.Accessiblebyall": "TRUE",
    "Agent3.Name": "AMDEPYC774264-CoreProcessor",
    "Agent3.Uuid": "CPU-XX",
    "Agent3.MarketingName": "AMDEPYC774264-CoreProcessor",
    "Agent3.VendorName": "CPU",
    "Agent3.Feature": "Nonespecified",
    "Agent3.Profile": "FULL_PROFILE",
    "Agent3.FloatRoundMode": "NEAR",
    "Agent3.MaxQueueNumber": "0(0x0)",
    "Agent3.QueueMinSize": "0(0x0)",
    "Agent3.QueueMaxSize": "0(0x0)",
    "Agent3.QueueType": "MULTI",
    "Agent3.Node": "2",
    "Agent3.DeviceType": "CPU",
    "Agent3.CacheInfo.L1": "32768(0x8000)KB",
    "Agent3.ChipID": "0(0x0)",
    "Agent3.ASICRevision": "0(0x0)",
    "Agent3.CachelineSize": "64(0x40)",
    "Agent3.MaxClockFreq.(MHz)": "2250",
    "Agent3.BDFID": "0",
    "Agent3.InternalNodeID": "2",
    "Agent3.ComputeUnit": "16",
    "Agent3.SIMDsperCU": "0",
    "Agent3.ShaderEngines": "0",
    "Agent3.ShaderArrs.perEng.": "0",
    "Agent3.WatchPtsonAddr.Ranges": "1",
    "Agent3.MemoryProperties.Features": "None",
    "Agent3.MemoryProperties.PoolInfo.Pool1.Segment": "GLOBAL",
    "Agent3.MemoryProperties.PoolInfo.Pool1.FLAGS": "FINEGRAINED",
    "Agent3.MemoryProperties.PoolInfo.Pool1.Size": "66055088(0x3efebb0)KB",
    "Agent3.MemoryProperties.PoolInfo.Pool1.Allocatable": "TRUE",
    "Agent3.MemoryProperties.PoolInfo.Pool1.AllocGranule": "4KB",
    "Agent3.MemoryProperties.PoolInfo.Pool1.AllocRecommendedGranule": "4KB",
    "Agent3.MemoryProperties.PoolInfo.Pool1.AllocAlignment": "4KB",
    "Agent3.MemoryProperties.PoolInfo.Pool1.Accessiblebyall": "TRUE",
    "Agent3.MemoryProperties.PoolInfo.Pool2.Segment": "GLOBAL",
    "Agent3.MemoryProperties.PoolInfo.Pool2.FLAGS": "EXTENDEDFINEGRAINED",
    "Agent3.MemoryProperties.PoolInfo.Pool2.Size": "66055088(0x3efebb0)KB",
    "Agent3.MemoryProperties.PoolInfo.Pool2.Allocatable": "TRUE",
    "Agent3.MemoryProperties.PoolInfo.Pool2.AllocGranule": "4KB",
    "Agent3.MemoryProperties.PoolInfo.Pool2.AllocRecommendedGranule": "4KB",
    "Agent3.MemoryProperties.PoolInfo.Pool2.AllocAlignment": "4KB",
    "Agent3.MemoryProperties.PoolInfo.Pool2.Accessiblebyall": "TRUE",
    "Agent3.MemoryProperties.PoolInfo.Pool3.Segment": "GLOBAL",
    "Agent3.MemoryProperties.PoolInfo.Pool3.FLAGS": "KERNARG,FINEGRAINED",
    "Agent3.MemoryProperties.PoolInfo.Pool3.Size": "66055088(0x3efebb0)KB",
    "Agent3.MemoryProperties.PoolInfo.Pool3.Allocatable": "TRUE",
    "Agent3.MemoryProperties.PoolInfo.Pool3.AllocGranule": "4KB",
    "Agent3.MemoryProperties.PoolInfo.Pool3.AllocRecommendedGranule": "4KB",
    "Agent3.MemoryProperties.PoolInfo.Pool3.AllocAlignment": "4KB",
    "Agent3.MemoryProperties.PoolInfo.Pool3.Accessiblebyall": "TRUE",
    "Agent3.MemoryProperties.PoolInfo.Pool4.Segment": "GLOBAL",
    "Agent3.MemoryProperties.PoolInfo.Pool4.FLAGS": "COARSEGRAINED",
    "Agent3.MemoryProperties.PoolInfo.Pool4.Size": "66055088(0x3efebb0)KB",
    "Agent3.MemoryProperties.PoolInfo.Pool4.Allocatable": "TRUE",
    "Agent3.MemoryProperties.PoolInfo.Pool4.AllocGranule": "4KB",
    "Agent3.MemoryProperties.PoolInfo.Pool4.AllocRecommendedGranule": "4KB",
    "Agent3.MemoryProperties.PoolInfo.Pool4.AllocAlignment": "4KB",
    "Agent3.MemoryProperties.PoolInfo.Pool4.Accessiblebyall": "TRUE",
    "Agent4.Name": "AMDEPYC774264-CoreProcessor",
    "Agent4.Uuid": "CPU-XX",
    "Agent4.MarketingName": "AMDEPYC774264-CoreProcessor",
    "Agent4.VendorName": "CPU",
    "Agent4.Feature": "Nonespecified",
    "Agent4.Profile": "FULL_PROFILE",
    "Agent4.FloatRoundMode": "NEAR",
    "Agent4.MaxQueueNumber": "0(0x0)",
    "Agent4.QueueMinSize": "0(0x0)",
    "Agent4.QueueMaxSize": "0(0x0)",
    "Agent4.QueueType": "MULTI",
    "Agent4.Node": "3",
    "Agent4.DeviceType": "CPU",
    "Agent4.CacheInfo.L1": "32768(0x8000)KB",
    "Agent4.ChipID": "0(0x0)",
    "Agent4.ASICRevision": "0(0x0)",
    "Agent4.CachelineSize": "64(0x40)",
    "Agent4.MaxClockFreq.(MHz)": "2250",
    "Agent4.BDFID": "0",
    "Agent4.InternalNodeID": "3",
    "Agent4.ComputeUnit": "16",
    "Agent4.SIMDsperCU": "0",
    "Agent4.ShaderEngines": "0",
    "Agent4.ShaderArrs.perEng.": "0",
    "Agent4.WatchPtsonAddr.Ranges": "1",
    "Agent4.MemoryProperties.Features": "None",
    "Agent4.MemoryProperties.PoolInfo.Pool1.Segment": "GLOBAL",
    "Agent4.MemoryProperties.PoolInfo.Pool1.FLAGS": "FINEGRAINED",
    "Agent4.MemoryProperties.PoolInfo.Pool1.Size": "65994088(0x3eefd68)KB",
    "Agent4.MemoryProperties.PoolInfo.Pool1.Allocatable": "TRUE",
    "Agent4.MemoryProperties.PoolInfo.Pool1.AllocGranule": "4KB",
    "Agent4.MemoryProperties.PoolInfo.Pool1.AllocRecommendedGranule": "4KB",
    "Agent4.MemoryProperties.PoolInfo.Pool1.AllocAlignment": "4KB",
    "Agent4.MemoryProperties.PoolInfo.Pool1.Accessiblebyall": "TRUE",
    "Agent4.MemoryProperties.PoolInfo.Pool2.Segment": "GLOBAL",
    "Agent4.MemoryProperties.PoolInfo.Pool2.FLAGS": "EXTENDEDFINEGRAINED",
    "Agent4.MemoryProperties.PoolInfo.Pool2.Size": "65994088(0x3eefd68)KB",
    "Agent4.MemoryProperties.PoolInfo.Pool2.Allocatable": "TRUE",
    "Agent4.MemoryProperties.PoolInfo.Pool2.AllocGranule": "4KB",
    "Agent4.MemoryProperties.PoolInfo.Pool2.AllocRecommendedGranule": "4KB",
    "Agent4.MemoryProperties.PoolInfo.Pool2.AllocAlignment": "4KB",
    "Agent4.MemoryProperties.PoolInfo.Pool2.Accessiblebyall": "TRUE",
    "Agent4.MemoryProperties.PoolInfo.Pool3.Segment": "GLOBAL",
    "Agent4.MemoryProperties.PoolInfo.Pool3.FLAGS": "KERNARG,FINEGRAINED",
    "Agent4.MemoryProperties.PoolInfo.Pool3.Size": "65994088(0x3eefd68)KB",
    "Agent4.MemoryProperties.PoolInfo.Pool3.Allocatable": "TRUE",
    "Agent4.MemoryProperties.PoolInfo.Pool3.AllocGranule": "4KB",
    "Agent4.MemoryProperties.PoolInfo.Pool3.AllocRecommendedGranule": "4KB",
    "Agent4.MemoryProperties.PoolInfo.Pool3.AllocAlignment": "4KB",
    "Agent4.MemoryProperties.PoolInfo.Pool3.Accessiblebyall": "TRUE",
    "Agent4.MemoryProperties.PoolInfo.Pool4.Segment": "GLOBAL",
    "Agent4.MemoryProperties.PoolInfo.Pool4.FLAGS": "COARSEGRAINED",
    "Agent4.MemoryProperties.PoolInfo.Pool4.Size": "65994088(0x3eefd68)KB",
    "Agent4.MemoryProperties.PoolInfo.Pool4.Allocatable": "TRUE",
    "Agent4.MemoryProperties.PoolInfo.Pool4.AllocGranule": "4KB",
    "Agent4.MemoryProperties.PoolInfo.Pool4.AllocRecommendedGranule": "4KB",
    "Agent4.MemoryProperties.PoolInfo.Pool4.AllocAlignment": "4KB",
    "Agent4.MemoryProperties.PoolInfo.Pool4.Accessiblebyall": "TRUE",
    "Agent5.Name": "AMDEPYC774264-CoreProcessor",
    "Agent5.Uuid": "CPU-XX",
    "Agent5.MarketingName": "AMDEPYC774264-CoreProcessor",
    "Agent5.VendorName": "CPU",
    "Agent5.Feature": "Nonespecified",
    "Agent5.Profile": "FULL_PROFILE",
    "Agent5.FloatRoundMode": "NEAR",
    "Agent5.MaxQueueNumber": "0(0x0)",
    "Agent5.QueueMinSize": "0(0x0)",
    "Agent5.QueueMaxSize": "0(0x0)",
    "Agent5.QueueType": "MULTI",
    "Agent5.Node": "4",
    "Agent5.DeviceType": "CPU",
    "Agent5.CacheInfo.L1": "32768(0x8000)KB",
    "Agent5.ChipID": "0(0x0)",
    "Agent5.ASICRevision": "0(0x0)",
    "Agent5.CachelineSize": "64(0x40)",
    "Agent5.MaxClockFreq.(MHz)": "2250",
    "Agent5.BDFID": "0",
    "Agent5.InternalNodeID": "4",
    "Agent5.ComputeUnit": "16",
    "Agent5.SIMDsperCU": "0",
    "Agent5.ShaderEngines": "0",
    "Agent5.ShaderArrs.perEng.": "0",
    "Agent5.WatchPtsonAddr.Ranges": "1",
    "Agent5.MemoryProperties.Features": "None",
    "Agent5.MemoryProperties.PoolInfo.Pool1.Segment": "GLOBAL",
    "Agent5.MemoryProperties.PoolInfo.Pool1.FLAGS": "FINEGRAINED",
    "Agent5.MemoryProperties.PoolInfo.Pool1.Size": "66055088(0x3efebb0)KB",
    "Agent5.MemoryProperties.PoolInfo.Pool1.Allocatable": "TRUE",
    "Agent5.MemoryProperties.PoolInfo.Pool1.AllocGranule": "4KB",
    "Agent5.MemoryProperties.PoolInfo.Pool1.AllocRecommendedGranule": "4KB",
    "Agent5.MemoryProperties.PoolInfo.Pool1.AllocAlignment": "4KB",
    "Agent5.MemoryProperties.PoolInfo.Pool1.Accessiblebyall": "TRUE",
    "Agent5.MemoryProperties.PoolInfo.Pool2.Segment": "GLOBAL",
    "Agent5.MemoryProperties.PoolInfo.Pool2.FLAGS": "EXTENDEDFINEGRAINED",
    "Agent5.MemoryProperties.PoolInfo.Pool2.Size": "66055088(0x3efebb0)KB",
    "Agent5.MemoryProperties.PoolInfo.Pool2.Allocatable": "TRUE",
    "Agent5.MemoryProperties.PoolInfo.Pool2.AllocGranule": "4KB",
    "Agent5.MemoryProperties.PoolInfo.Pool2.AllocRecommendedGranule": "4KB",
    "Agent5.MemoryProperties.PoolInfo.Pool2.AllocAlignment": "4KB",
    "Agent5.MemoryProperties.PoolInfo.Pool2.Accessiblebyall": "TRUE",
    "Agent5.MemoryProperties.PoolInfo.Pool3.Segment": "GLOBAL",
    "Agent5.MemoryProperties.PoolInfo.Pool3.FLAGS": "KERNARG,FINEGRAINED",
    "Agent5.MemoryProperties.PoolInfo.Pool3.Size": "66055088(0x3efebb0)KB",
    "Agent5.MemoryProperties.PoolInfo.Pool3.Allocatable": "TRUE",
    "Agent5.MemoryProperties.PoolInfo.Pool3.AllocGranule": "4KB",
    "Agent5.MemoryProperties.PoolInfo.Pool3.AllocRecommendedGranule": "4KB",
    "Agent5.MemoryProperties.PoolInfo.Pool3.AllocAlignment": "4KB",
    "Agent5.MemoryProperties.PoolInfo.Pool3.Accessiblebyall": "TRUE",
    "Agent5.MemoryProperties.PoolInfo.Pool4.Segment": "GLOBAL",
    "Agent5.MemoryProperties.PoolInfo.Pool4.FLAGS": "COARSEGRAINED",
    "Agent5.MemoryProperties.PoolInfo.Pool4.Size": "66055088(0x3efebb0)KB",
    "Agent5.MemoryProperties.PoolInfo.Pool4.Allocatable": "TRUE",
    "Agent5.MemoryProperties.PoolInfo.Pool4.AllocGranule": "4KB",
    "Agent5.MemoryProperties.PoolInfo.Pool4.AllocRecommendedGranule": "4KB",
    "Agent5.MemoryProperties.PoolInfo.Pool4.AllocAlignment": "4KB",
    "Agent5.MemoryProperties.PoolInfo.Pool4.Accessiblebyall": "TRUE",
    "Agent6.Name": "AMDEPYC774264-CoreProcessor",
    "Agent6.Uuid": "CPU-XX",
    "Agent6.MarketingName": "AMDEPYC774264-CoreProcessor",
    "Agent6.VendorName": "CPU",
    "Agent6.Feature": "Nonespecified",
    "Agent6.Profile": "FULL_PROFILE",
    "Agent6.FloatRoundMode": "NEAR",
    "Agent6.MaxQueueNumber": "0(0x0)",
    "Agent6.QueueMinSize": "0(0x0)",
    "Agent6.QueueMaxSize": "0(0x0)",
    "Agent6.QueueType": "MULTI",
    "Agent6.Node": "5",
    "Agent6.DeviceType": "CPU",
    "Agent6.CacheInfo.L1": "32768(0x8000)KB",
    "Agent6.ChipID": "0(0x0)",
    "Agent6.ASICRevision": "0(0x0)",
    "Agent6.CachelineSize": "64(0x40)",
    "Agent6.MaxClockFreq.(MHz)": "2250",
    "Agent6.BDFID": "0",
    "Agent6.InternalNodeID": "5",
    "Agent6.ComputeUnit": "16",
    "Agent6.SIMDsperCU": "0",
    "Agent6.ShaderEngines": "0",
    "Agent6.ShaderArrs.perEng.": "0",
    "Agent6.WatchPtsonAddr.Ranges": "1",
    "Agent6.MemoryProperties.Features": "None",
    "Agent6.MemoryProperties.PoolInfo.Pool1.Segment": "GLOBAL",
    "Agent6.MemoryProperties.PoolInfo.Pool1.FLAGS": "FINEGRAINED",
    "Agent6.MemoryProperties.PoolInfo.Pool1.Size": "66055088(0x3efebb0)KB",
    "Agent6.MemoryProperties.PoolInfo.Pool1.Allocatable": "TRUE",
    "Agent6.MemoryProperties.PoolInfo.Pool1.AllocGranule": "4KB",
    "Agent6.MemoryProperties.PoolInfo.Pool1.AllocRecommendedGranule": "4KB",
    "Agent6.MemoryProperties.PoolInfo.Pool1.AllocAlignment": "4KB",
    "Agent6.MemoryProperties.PoolInfo.Pool1.Accessiblebyall": "TRUE",
    "Agent6.MemoryProperties.PoolInfo.Pool2.Segment": "GLOBAL",
    "Agent6.MemoryProperties.PoolInfo.Pool2.FLAGS": "EXTENDEDFINEGRAINED",
    "Agent6.MemoryProperties.PoolInfo.Pool2.Size": "66055088(0x3efebb0)KB",
    "Agent6.MemoryProperties.PoolInfo.Pool2.Allocatable": "TRUE",
    "Agent6.MemoryProperties.PoolInfo.Pool2.AllocGranule": "4KB",
    "Agent6.MemoryProperties.PoolInfo.Pool2.AllocRecommendedGranule": "4KB",
    "Agent6.MemoryProperties.PoolInfo.Pool2.AllocAlignment": "4KB",
    "Agent6.MemoryProperties.PoolInfo.Pool2.Accessiblebyall": "TRUE",
    "Agent6.MemoryProperties.PoolInfo.Pool3.Segment": "GLOBAL",
    "Agent6.MemoryProperties.PoolInfo.Pool3.FLAGS": "KERNARG,FINEGRAINED",
    "Agent6.MemoryProperties.PoolInfo.Pool3.Size": "66055088(0x3efebb0)KB",
    "Agent6.MemoryProperties.PoolInfo.Pool3.Allocatable": "TRUE",
    "Agent6.MemoryProperties.PoolInfo.Pool3.AllocGranule": "4KB",
    "Agent6.MemoryProperties.PoolInfo.Pool3.AllocRecommendedGranule": "4KB",
    "Agent6.MemoryProperties.PoolInfo.Pool3.AllocAlignment": "4KB",
    "Agent6.MemoryProperties.PoolInfo.Pool3.Accessiblebyall": "TRUE",
    "Agent6.MemoryProperties.PoolInfo.Pool4.Segment": "GLOBAL",
    "Agent6.MemoryProperties.PoolInfo.Pool4.FLAGS": "COARSEGRAINED",
    "Agent6.MemoryProperties.PoolInfo.Pool4.Size": "66055088(0x3efebb0)KB",
    "Agent6.MemoryProperties.PoolInfo.Pool4.Allocatable": "TRUE",
    "Agent6.MemoryProperties.PoolInfo.Pool4.AllocGranule": "4KB",
    "Agent6.MemoryProperties.PoolInfo.Pool4.AllocRecommendedGranule": "4KB",
    "Agent6.MemoryProperties.PoolInfo.Pool4.AllocAlignment": "4KB",
    "Agent6.MemoryProperties.PoolInfo.Pool4.Accessiblebyall": "TRUE",
    "Agent7.Name": "AMDEPYC774264-CoreProcessor",
    "Agent7.Uuid": "CPU-XX",
    "Agent7.MarketingName": "AMDEPYC774264-CoreProcessor",
    "Agent7.VendorName": "CPU",
    "Agent7.Feature": "Nonespecified",
    "Agent7.Profile": "FULL_PROFILE",
    "Agent7.FloatRoundMode": "NEAR",
    "Agent7.MaxQueueNumber": "0(0x0)",
    "Agent7.QueueMinSize": "0(0x0)",
    "Agent7.QueueMaxSize": "0(0x0)",
    "Agent7.QueueType": "MULTI",
    "Agent7.Node": "6",
    "Agent7.DeviceType": "CPU",
    "Agent7.CacheInfo.L1": "32768(0x8000)KB",
    "Agent7.ChipID": "0(0x0)",
    "Agent7.ASICRevision": "0(0x0)",
    "Agent7.CachelineSize": "64(0x40)",
    "Agent7.MaxClockFreq.(MHz)": "2250",
    "Agent7.BDFID": "0",
    "Agent7.InternalNodeID": "6",
    "Agent7.ComputeUnit": "16",
    "Agent7.SIMDsperCU": "0",
    "Agent7.ShaderEngines": "0",
    "Agent7.ShaderArrs.perEng.": "0",
    "Agent7.WatchPtsonAddr.Ranges": "1",
    "Agent7.MemoryProperties.Features": "None",
    "Agent7.MemoryProperties.PoolInfo.Pool1.Segment": "GLOBAL",
    "Agent7.MemoryProperties.PoolInfo.Pool1.FLAGS": "FINEGRAINED",
    "Agent7.MemoryProperties.PoolInfo.Pool1.Size": "66055088(0x3efebb0)KB",
    "Agent7.MemoryProperties.PoolInfo.Pool1.Allocatable": "TRUE",
    "Agent7.MemoryProperties.PoolInfo.Pool1.AllocGranule": "4KB",
    "Agent7.MemoryProperties.PoolInfo.Pool1.AllocRecommendedGranule": "4KB",
    "Agent7.MemoryProperties.PoolInfo.Pool1.AllocAlignment": "4KB",
    "Agent7.MemoryProperties.PoolInfo.Pool1.Accessiblebyall": "TRUE",
    "Agent7.MemoryProperties.PoolInfo.Pool2.Segment": "GLOBAL",
    "Agent7.MemoryProperties.PoolInfo.Pool2.FLAGS": "EXTENDEDFINEGRAINED",
    "Agent7.MemoryProperties.PoolInfo.Pool2.Size": "66055088(0x3efebb0)KB",
    "Agent7.MemoryProperties.PoolInfo.Pool2.Allocatable": "TRUE",
    "Agent7.MemoryProperties.PoolInfo.Pool2.AllocGranule": "4KB",
    "Agent7.MemoryProperties.PoolInfo.Pool2.AllocRecommendedGranule": "4KB",
    "Agent7.MemoryProperties.PoolInfo.Pool2.AllocAlignment": "4KB",
    "Agent7.MemoryProperties.PoolInfo.Pool2.Accessiblebyall": "TRUE",
    "Agent7.MemoryProperties.PoolInfo.Pool3.Segment": "GLOBAL",
    "Agent7.MemoryProperties.PoolInfo.Pool3.FLAGS": "KERNARG,FINEGRAINED",
    "Agent7.MemoryProperties.PoolInfo.Pool3.Size": "66055088(0x3efebb0)KB",
    "Agent7.MemoryProperties.PoolInfo.Pool3.Allocatable": "TRUE",
    "Agent7.MemoryProperties.PoolInfo.Pool3.AllocGranule": "4KB",
    "Agent7.MemoryProperties.PoolInfo.Pool3.AllocRecommendedGranule": "4KB",
    "Agent7.MemoryProperties.PoolInfo.Pool3.AllocAlignment": "4KB",
    "Agent7.MemoryProperties.PoolInfo.Pool3.Accessiblebyall": "TRUE",
    "Agent7.MemoryProperties.PoolInfo.Pool4.Segment": "GLOBAL",
    "Agent7.MemoryProperties.PoolInfo.Pool4.FLAGS": "COARSEGRAINED",
    "Agent7.MemoryProperties.PoolInfo.Pool4.Size": "66055088(0x3efebb0)KB",
    "Agent7.MemoryProperties.PoolInfo.Pool4.Allocatable": "TRUE",
    "Agent7.MemoryProperties.PoolInfo.Pool4.AllocGranule": "4KB",
    "Agent7.MemoryProperties.PoolInfo.Pool4.AllocRecommendedGranule": "4KB",
    "Agent7.MemoryProperties.PoolInfo.Pool4.AllocAlignment": "4KB",
    "Agent7.MemoryProperties.PoolInfo.Pool4.Accessiblebyall": "TRUE",
    "Agent8.Name": "AMDEPYC774264-CoreProcessor",
    "Agent8.Uuid": "CPU-XX",
    "Agent8.MarketingName": "AMDEPYC774264-CoreProcessor",
    "Agent8.VendorName": "CPU",
    "Agent8.Feature": "Nonespecified",
    "Agent8.Profile": "FULL_PROFILE",
    "Agent8.FloatRoundMode": "NEAR",
    "Agent8.MaxQueueNumber": "0(0x0)",
    "Agent8.QueueMinSize": "0(0x0)",
    "Agent8.QueueMaxSize": "0(0x0)",
    "Agent8.QueueType": "MULTI",
    "Agent8.Node": "7",
    "Agent8.DeviceType": "CPU",
    "Agent8.CacheInfo.L1": "32768(0x8000)KB",
    "Agent8.ChipID": "0(0x0)",
    "Agent8.ASICRevision": "0(0x0)",
    "Agent8.CachelineSize": "64(0x40)",
    "Agent8.MaxClockFreq.(MHz)": "2250",
    "Agent8.BDFID": "0",
    "Agent8.InternalNodeID": "7",
    "Agent8.ComputeUnit": "16",
    "Agent8.SIMDsperCU": "0",
    "Agent8.ShaderEngines": "0",
    "Agent8.ShaderArrs.perEng.": "0",
    "Agent8.WatchPtsonAddr.Ranges": "1",
    "Agent8.MemoryProperties.Features": "None",
    "Agent8.MemoryProperties.PoolInfo.Pool1.Segment": "GLOBAL",
    "Agent8.MemoryProperties.PoolInfo.Pool1.FLAGS": "FINEGRAINED",
    "Agent8.MemoryProperties.PoolInfo.Pool1.Size": "66048648(0x3efd288)KB",
    "Agent8.MemoryProperties.PoolInfo.Pool1.Allocatable": "TRUE",
    "Agent8.MemoryProperties.PoolInfo.Pool1.AllocGranule": "4KB",
    "Agent8.MemoryProperties.PoolInfo.Pool1.AllocRecommendedGranule": "4KB",
    "Agent8.MemoryProperties.PoolInfo.Pool1.AllocAlignment": "4KB",
    "Agent8.MemoryProperties.PoolInfo.Pool1.Accessiblebyall": "TRUE",
    "Agent8.MemoryProperties.PoolInfo.Pool2.Segment": "GLOBAL",
    "Agent8.MemoryProperties.PoolInfo.Pool2.FLAGS": "EXTENDEDFINEGRAINED",
    "Agent8.MemoryProperties.PoolInfo.Pool2.Size": "66048648(0x3efd288)KB",
    "Agent8.MemoryProperties.PoolInfo.Pool2.Allocatable": "TRUE",
    "Agent8.MemoryProperties.PoolInfo.Pool2.AllocGranule": "4KB",
    "Agent8.MemoryProperties.PoolInfo.Pool2.AllocRecommendedGranule": "4KB",
    "Agent8.MemoryProperties.PoolInfo.Pool2.AllocAlignment": "4KB",
    "Agent8.MemoryProperties.PoolInfo.Pool2.Accessiblebyall": "TRUE",
    "Agent8.MemoryProperties.PoolInfo.Pool3.Segment": "GLOBAL",
    "Agent8.MemoryProperties.PoolInfo.Pool3.FLAGS": "KERNARG,FINEGRAINED",
    "Agent8.MemoryProperties.PoolInfo.Pool3.Size": "66048648(0x3efd288)KB",
    "Agent8.MemoryProperties.PoolInfo.Pool3.Allocatable": "TRUE",
    "Agent8.MemoryProperties.PoolInfo.Pool3.AllocGranule": "4KB",
    "Agent8.MemoryProperties.PoolInfo.Pool3.AllocRecommendedGranule": "4KB",
    "Agent8.MemoryProperties.PoolInfo.Pool3.AllocAlignment": "4KB",
    "Agent8.MemoryProperties.PoolInfo.Pool3.Accessiblebyall": "TRUE",
    "Agent8.MemoryProperties.PoolInfo.Pool4.Segment": "GLOBAL",
    "Agent8.MemoryProperties.PoolInfo.Pool4.FLAGS": "COARSEGRAINED",
    "Agent8.MemoryProperties.PoolInfo.Pool4.Size": "66048648(0x3efd288)KB",
    "Agent8.MemoryProperties.PoolInfo.Pool4.Allocatable": "TRUE",
    "Agent8.MemoryProperties.PoolInfo.Pool4.AllocGranule": "4KB",
    "Agent8.MemoryProperties.PoolInfo.Pool4.AllocRecommendedGranule": "4KB",
    "Agent8.MemoryProperties.PoolInfo.Pool4.AllocAlignment": "4KB",
    "Agent8.MemoryProperties.PoolInfo.Pool4.Accessiblebyall": "TRUE",
    "Agent9.Name": "gfx908",
    "Agent9.Uuid": "GPU-e5afeb973f3e4287",
    "Agent9.MarketingName": "AMDInstinctMI100",
    "Agent9.VendorName": "AMD",
    "Agent9.Feature": "KERNEL_DISPATCH",
    "Agent9.Profile": "BASE_PROFILE",
    "Agent9.FloatRoundMode": "NEAR",
    "Agent9.MaxQueueNumber": "128(0x80)",
    "Agent9.QueueMinSize": "64(0x40)",
    "Agent9.QueueMaxSize": "131072(0x20000)",
    "Agent9.QueueType": "MULTI",
    "Agent9.Node": "8",
    "Agent9.DeviceType": "GPU",
    "Agent9.CacheInfo.L1": "16(0x10)KB",
    "Agent9.CacheInfo.L2": "8192(0x2000)KB",
    "Agent9.ChipID": "29580(0x738c)",
    "Agent9.ASICRevision": "2(0x2)",
    "Agent9.CachelineSize": "64(0x40)",
    "Agent9.MaxClockFreq.(MHz)": "1502",
    "Agent9.BDFID": "25344",
    "Agent9.InternalNodeID": "8",
    "Agent9.ComputeUnit": "120",
    "Agent9.SIMDsperCU": "4",
    "Agent9.ShaderEngines": "8",
    "Agent9.ShaderArrs.perEng.": "1",
    "Agent9.WatchPtsonAddr.Ranges": "4",
    "Agent9.CoherentHostAccess": "FALSE",
    "Agent9.MemoryProperties.Features": "KERNEL_DISPATCH",
    "Agent9.MemoryProperties.FastF16Operation": "TRUE",
    "Agent9.MemoryProperties.WavefrontSize": "64(0x40)",
    "Agent9.MemoryProperties.WorkgroupMaxSize": "1024(0x400)",
    "Agent9.MemoryProperties.WorkgroupMaxSizeperDimension.x": "1024(0x400)",
    "Agent9.MemoryProperties.WorkgroupMaxSizeperDimension.y": "1024(0x400)",
    "Agent9.MemoryProperties.WorkgroupMaxSizeperDimension.z": "1024(0x400)",
    "Agent9.MemoryProperties.MaxWavesPerCU": "40(0x28)",
    "Agent9.MemoryProperties.MaxWork-itemPerCU": "2560(0xa00)",
    "Agent9.MemoryProperties.GridMaxSize": "4294967295(0xffffffff)",
    "Agent9.MemoryProperties.GridMaxSizeperDimension.x": "4294967295(0xffffffff)",
    "Agent9.MemoryProperties.GridMaxSizeperDimension.y": "4294967295(0xffffffff)",
    "Agent9.MemoryProperties.GridMaxSizeperDimension.z": "4294967295(0xffffffff)",
    "Agent9.MemoryProperties.Maxfbarriers/Workgrp": "32",
    "Agent9.MemoryProperties.PacketProcessoruCode:": "60",
    "Agent9.MemoryProperties.SDMAengineuCode:": "18",
    "Agent9.MemoryProperties.IOMMUSupport:": "None",
    "Agent9.MemoryProperties.PoolInfo.Pool1.Segment": "GLOBAL",
    "Agent9.MemoryProperties.PoolInfo.Pool1.FLAGS": "COARSEGRAINED",
    "Agent9.MemoryProperties.PoolInfo.Pool1.Size": "33538048(0x1ffc000)KB",
    "Agent9.MemoryProperties.PoolInfo.Pool1.Allocatable": "TRUE",
    "Agent9.MemoryProperties.PoolInfo.Pool1.AllocGranule": "4KB",
    "Agent9.MemoryProperties.PoolInfo.Pool1.AllocRecommendedGranule": "2048KB",
    "Agent9.MemoryProperties.PoolInfo.Pool1.AllocAlignment": "4KB",
    "Agent9.MemoryProperties.PoolInfo.Pool1.Accessiblebyall": "FALSE",
    "Agent9.MemoryProperties.PoolInfo.Pool2.Segment": "GLOBAL",
    "Agent9.MemoryProperties.PoolInfo.Pool2.FLAGS": "EXTENDEDFINEGRAINED",
    "Agent9.MemoryProperties.PoolInfo.Pool2.Size": "33538048(0x1ffc000)KB",
    "Agent9.MemoryProperties.PoolInfo.Pool2.Allocatable": "TRUE",
    "Agent9.MemoryProperties.PoolInfo.Pool2.AllocGranule": "4KB",
    "Agent9.MemoryProperties.PoolInfo.Pool2.AllocRecommendedGranule": "2048KB",
    "Agent9.MemoryProperties.PoolInfo.Pool2.AllocAlignment": "4KB",
    "Agent9.MemoryProperties.PoolInfo.Pool2.Accessiblebyall": "FALSE",
    "Agent9.MemoryProperties.PoolInfo.Pool3.Segment": "GROUP",
    "Agent9.MemoryProperties.PoolInfo.Pool3.Size": "64(0x40)KB",
    "Agent9.MemoryProperties.PoolInfo.Pool3.Allocatable": "FALSE",
    "Agent9.MemoryProperties.PoolInfo.Pool3.AllocGranule": "0KB",
    "Agent9.MemoryProperties.PoolInfo.Pool3.AllocRecommendedGranule": "0KB",
    "Agent9.MemoryProperties.PoolInfo.Pool3.AllocAlignment": "0KB",
    "Agent9.MemoryProperties.PoolInfo.Pool3.Accessiblebyall": "FALSE",
    "Agent9.MemoryProperties.ISAInfo.ISA1.Name:amdgcn-amd-amdhsa--gfx908:sramecc+": "xnack-",
    "Agent9.MemoryProperties.ISAInfo.ISA1.MachineModels": "HSA_MACHINE_MODEL_LARGE",
    "Agent9.MemoryProperties.ISAInfo.ISA1.Profiles": "HSA_PROFILE_BASE",
    "Agent9.MemoryProperties.ISAInfo.ISA1.DefaultRoundingMode": "NEAR",
    "Agent9.MemoryProperties.ISAInfo.ISA1.DefaultRoundingMode": "NEAR",
    "Agent9.MemoryProperties.ISAInfo.ISA1.Fastf16": "TRUE",
    "Agent9.MemoryProperties.ISAInfo.ISA1.WorkgroupMaxSize": "1024(0x400)",
    "Agent9.MemoryProperties.ISAInfo.ISA1.WorkgroupMaxSizeperDimension.x": "1024(0x400)",
    "Agent9.MemoryProperties.ISAInfo.ISA1.WorkgroupMaxSizeperDimension.y": "1024(0x400)",
    "Agent9.MemoryProperties.ISAInfo.ISA1.WorkgroupMaxSizeperDimension.z": "1024(0x400)",
    "Agent9.MemoryProperties.ISAInfo.ISA1.GridMaxSize": "4294967295(0xffffffff)",
    "Agent9.MemoryProperties.ISAInfo.ISA1.GridMaxSizeperDimension.x": "4294967295(0xffffffff)",
    "Agent9.MemoryProperties.ISAInfo.ISA1.GridMaxSizeperDimension.y": "4294967295(0xffffffff)",
    "Agent9.MemoryProperties.ISAInfo.ISA1.GridMaxSizeperDimension.z": "4294967295(0xffffffff)",
    "Agent9.MemoryProperties.ISAInfo.ISA1.FBarrierMaxSize": "32",
    "Agent10.Name": "gfx908",
    "Agent10.Uuid": "GPU-3ac4b60f2e7bd428",
    "Agent10.MarketingName": "AMDInstinctMI100",
    "Agent10.VendorName": "AMD",
    "Agent10.Feature": "KERNEL_DISPATCH",
    "Agent10.Profile": "BASE_PROFILE",
    "Agent10.FloatRoundMode": "NEAR",
    "Agent10.MaxQueueNumber": "128(0x80)",
    "Agent10.QueueMinSize": "64(0x40)",
    "Agent10.QueueMaxSize": "131072(0x20000)",
    "Agent10.QueueType": "MULTI",
    "Agent10.Node": "9",
    "Agent10.DeviceType": "GPU",
    "Agent10.CacheInfo.L1": "16(0x10)KB",
    "Agent10.CacheInfo.L2": "8192(0x2000)KB",
    "Agent10.ChipID": "29580(0x738c)",
    "Agent10.ASICRevision": "2(0x2)",
    "Agent10.CachelineSize": "64(0x40)",
    "Agent10.MaxClockFreq.(MHz)": "1502",
    "Agent10.BDFID": "17152",
    "Agent10.InternalNodeID": "9",
    "Agent10.ComputeUnit": "120",
    "Agent10.SIMDsperCU": "4",
    "Agent10.ShaderEngines": "8",
    "Agent10.ShaderArrs.perEng.": "1",
    "Agent10.WatchPtsonAddr.Ranges": "4",
    "Agent10.CoherentHostAccess": "FALSE",
    "Agent10.MemoryProperties.Features": "KERNEL_DISPATCH",
    "Agent10.MemoryProperties.FastF16Operation": "TRUE",
    "Agent10.MemoryProperties.WavefrontSize": "64(0x40)",
    "Agent10.MemoryProperties.WorkgroupMaxSize": "1024(0x400)",
    "Agent10.MemoryProperties.WorkgroupMaxSizeperDimension.x": "1024(0x400)",
    "Agent10.MemoryProperties.WorkgroupMaxSizeperDimension.y": "1024(0x400)",
    "Agent10.MemoryProperties.WorkgroupMaxSizeperDimension.z": "1024(0x400)",
    "Agent10.MemoryProperties.MaxWavesPerCU": "40(0x28)",
    "Agent10.MemoryProperties.MaxWork-itemPerCU": "2560(0xa00)",
    "Agent10.MemoryProperties.GridMaxSize": "4294967295(0xffffffff)",
    "Agent10.MemoryProperties.GridMaxSizeperDimension.x": "4294967295(0xffffffff)",
    "Agent10.MemoryProperties.GridMaxSizeperDimension.y": "4294967295(0xffffffff)",
    "Agent10.MemoryProperties.GridMaxSizeperDimension.z": "4294967295(0xffffffff)",
    "Agent10.MemoryProperties.Maxfbarriers/Workgrp": "32",
    "Agent10.MemoryProperties.PacketProcessoruCode:": "60",
    "Agent10.MemoryProperties.SDMAengineuCode:": "18",
    "Agent10.MemoryProperties.IOMMUSupport:": "None",
    "Agent10.MemoryProperties.PoolInfo.Pool1.Segment": "GLOBAL",
    "Agent10.MemoryProperties.PoolInfo.Pool1.FLAGS": "COARSEGRAINED",
    "Agent10.MemoryProperties.PoolInfo.Pool1.Size": "33538048(0x1ffc000)KB",
    "Agent10.MemoryProperties.PoolInfo.Pool1.Allocatable": "TRUE",
    "Agent10.MemoryProperties.PoolInfo.Pool1.AllocGranule": "4KB",
    "Agent10.MemoryProperties.PoolInfo.Pool1.AllocRecommendedGranule": "2048KB",
    "Agent10.MemoryProperties.PoolInfo.Pool1.AllocAlignment": "4KB",
    "Agent10.MemoryProperties.PoolInfo.Pool1.Accessiblebyall": "FALSE",
    "Agent10.MemoryProperties.PoolInfo.Pool2.Segment": "GLOBAL",
    "Agent10.MemoryProperties.PoolInfo.Pool2.FLAGS": "EXTENDEDFINEGRAINED",
    "Agent10.MemoryProperties.PoolInfo.Pool2.Size": "33538048(0x1ffc000)KB",
    "Agent10.MemoryProperties.PoolInfo.Pool2.Allocatable": "TRUE",
    "Agent10.MemoryProperties.PoolInfo.Pool2.AllocGranule": "4KB",
    "Agent10.MemoryProperties.PoolInfo.Pool2.AllocRecommendedGranule": "2048KB",
    "Agent10.MemoryProperties.PoolInfo.Pool2.AllocAlignment": "4KB",
    "Agent10.MemoryProperties.PoolInfo.Pool2.Accessiblebyall": "FALSE",
    "Agent10.MemoryProperties.PoolInfo.Pool3.Segment": "GROUP",
    "Agent10.MemoryProperties.PoolInfo.Pool3.Size": "64(0x40)KB",
    "Agent10.MemoryProperties.PoolInfo.Pool3.Allocatable": "FALSE",
    "Agent10.MemoryProperties.PoolInfo.Pool3.AllocGranule": "0KB",
    "Agent10.MemoryProperties.PoolInfo.Pool3.AllocRecommendedGranule": "0KB",
    "Agent10.MemoryProperties.PoolInfo.Pool3.AllocAlignment": "0KB",
    "Agent10.MemoryProperties.PoolInfo.Pool3.Accessiblebyall": "FALSE",
    "Agent10.MemoryProperties.ISAInfo.ISA1.Name:amdgcn-amd-amdhsa--gfx908:sramecc+": "xnack-",
    "Agent10.MemoryProperties.ISAInfo.ISA1.MachineModels": "HSA_MACHINE_MODEL_LARGE",
    "Agent10.MemoryProperties.ISAInfo.ISA1.Profiles": "HSA_PROFILE_BASE",
    "Agent10.MemoryProperties.ISAInfo.ISA1.DefaultRoundingMode": "NEAR",
    "Agent10.MemoryProperties.ISAInfo.ISA1.DefaultRoundingMode": "NEAR",
    "Agent10.MemoryProperties.ISAInfo.ISA1.Fastf16": "TRUE",
    "Agent10.MemoryProperties.ISAInfo.ISA1.WorkgroupMaxSize": "1024(0x400)",
    "Agent10.MemoryProperties.ISAInfo.ISA1.WorkgroupMaxSizeperDimension.x": "1024(0x400)",
    "Agent10.MemoryProperties.ISAInfo.ISA1.WorkgroupMaxSizeperDimension.y": "1024(0x400)",
    "Agent10.MemoryProperties.ISAInfo.ISA1.WorkgroupMaxSizeperDimension.z": "1024(0x400)",
    "Agent10.MemoryProperties.ISAInfo.ISA1.GridMaxSize": "4294967295(0xffffffff)",
    "Agent10.MemoryProperties.ISAInfo.ISA1.GridMaxSizeperDimension.x": "4294967295(0xffffffff)",
    "Agent10.MemoryProperties.ISAInfo.ISA1.GridMaxSizeperDimension.y": "4294967295(0xffffffff)",
    "Agent10.MemoryProperties.ISAInfo.ISA1.GridMaxSizeperDimension.z": "4294967295(0xffffffff)",
    "Agent10.MemoryProperties.ISAInfo.ISA1.FBarrierMaxSize": "32",
    "Agent11.Name": "gfx908",
    "Agent11.Uuid": "GPU-1b14fab287632540",
    "Agent11.MarketingName": "AMDInstinctMI100",
    "Agent11.VendorName": "AMD",
    "Agent11.Feature": "KERNEL_DISPATCH",
    "Agent11.Profile": "BASE_PROFILE",
    "Agent11.FloatRoundMode": "NEAR",
    "Agent11.MaxQueueNumber": "128(0x80)",
    "Agent11.QueueMinSize": "64(0x40)",
    "Agent11.QueueMaxSize": "131072(0x20000)",
    "Agent11.QueueType": "MULTI",
    "Agent11.Node": "10",
    "Agent11.DeviceType": "GPU",
    "Agent11.CacheInfo.L1": "16(0x10)KB",
    "Agent11.CacheInfo.L2": "8192(0x2000)KB",
    "Agent11.ChipID": "29580(0x738c)",
    "Agent11.ASICRevision": "2(0x2)",
    "Agent11.CachelineSize": "64(0x40)",
    "Agent11.MaxClockFreq.(MHz)": "1502",
    "Agent11.BDFID": "9728",
    "Agent11.InternalNodeID": "10",
    "Agent11.ComputeUnit": "120",
    "Agent11.SIMDsperCU": "4",
    "Agent11.ShaderEngines": "8",
    "Agent11.ShaderArrs.perEng.": "1",
    "Agent11.WatchPtsonAddr.Ranges": "4",
    "Agent11.CoherentHostAccess": "FALSE",
    "Agent11.MemoryProperties.Features": "KERNEL_DISPATCH",
    "Agent11.MemoryProperties.FastF16Operation": "TRUE",
    "Agent11.MemoryProperties.WavefrontSize": "64(0x40)",
    "Agent11.MemoryProperties.WorkgroupMaxSize": "1024(0x400)",
    "Agent11.MemoryProperties.WorkgroupMaxSizeperDimension.x": "1024(0x400)",
    "Agent11.MemoryProperties.WorkgroupMaxSizeperDimension.y": "1024(0x400)",
    "Agent11.MemoryProperties.WorkgroupMaxSizeperDimension.z": "1024(0x400)",
    "Agent11.MemoryProperties.MaxWavesPerCU": "40(0x28)",
    "Agent11.MemoryProperties.MaxWork-itemPerCU": "2560(0xa00)",
    "Agent11.MemoryProperties.GridMaxSize": "4294967295(0xffffffff)",
    "Agent11.MemoryProperties.GridMaxSizeperDimension.x": "4294967295(0xffffffff)",
    "Agent11.MemoryProperties.GridMaxSizeperDimension.y": "4294967295(0xffffffff)",
    "Agent11.MemoryProperties.GridMaxSizeperDimension.z": "4294967295(0xffffffff)",
    "Agent11.MemoryProperties.Maxfbarriers/Workgrp": "32",
    "Agent11.MemoryProperties.PacketProcessoruCode:": "60",
    "Agent11.MemoryProperties.SDMAengineuCode:": "18",
    "Agent11.MemoryProperties.IOMMUSupport:": "None",
    "Agent11.MemoryProperties.PoolInfo.Pool1.Segment": "GLOBAL",
    "Agent11.MemoryProperties.PoolInfo.Pool1.FLAGS": "COARSEGRAINED",
    "Agent11.MemoryProperties.PoolInfo.Pool1.Size": "33538048(0x1ffc000)KB",
    "Agent11.MemoryProperties.PoolInfo.Pool1.Allocatable": "TRUE",
    "Agent11.MemoryProperties.PoolInfo.Pool1.AllocGranule": "4KB",
    "Agent11.MemoryProperties.PoolInfo.Pool1.AllocRecommendedGranule": "2048KB",
    "Agent11.MemoryProperties.PoolInfo.Pool1.AllocAlignment": "4KB",
    "Agent11.MemoryProperties.PoolInfo.Pool1.Accessiblebyall": "FALSE",
    "Agent11.MemoryProperties.PoolInfo.Pool2.Segment": "GLOBAL",
    "Agent11.MemoryProperties.PoolInfo.Pool2.FLAGS": "EXTENDEDFINEGRAINED",
    "Agent11.MemoryProperties.PoolInfo.Pool2.Size": "33538048(0x1ffc000)KB",
    "Agent11.MemoryProperties.PoolInfo.Pool2.Allocatable": "TRUE",
    "Agent11.MemoryProperties.PoolInfo.Pool2.AllocGranule": "4KB",
    "Agent11.MemoryProperties.PoolInfo.Pool2.AllocRecommendedGranule": "2048KB",
    "Agent11.MemoryProperties.PoolInfo.Pool2.AllocAlignment": "4KB",
    "Agent11.MemoryProperties.PoolInfo.Pool2.Accessiblebyall": "FALSE",
    "Agent11.MemoryProperties.PoolInfo.Pool3.Segment": "GROUP",
    "Agent11.MemoryProperties.PoolInfo.Pool3.Size": "64(0x40)KB",
    "Agent11.MemoryProperties.PoolInfo.Pool3.Allocatable": "FALSE",
    "Agent11.MemoryProperties.PoolInfo.Pool3.AllocGranule": "0KB",
    "Agent11.MemoryProperties.PoolInfo.Pool3.AllocRecommendedGranule": "0KB",
    "Agent11.MemoryProperties.PoolInfo.Pool3.AllocAlignment": "0KB",
    "Agent11.MemoryProperties.PoolInfo.Pool3.Accessiblebyall": "FALSE",
    "Agent11.MemoryProperties.ISAInfo.ISA1.Name:amdgcn-amd-amdhsa--gfx908:sramecc+": "xnack-",
    "Agent11.MemoryProperties.ISAInfo.ISA1.MachineModels": "HSA_MACHINE_MODEL_LARGE",
    "Agent11.MemoryProperties.ISAInfo.ISA1.Profiles": "HSA_PROFILE_BASE",
    "Agent11.MemoryProperties.ISAInfo.ISA1.DefaultRoundingMode": "NEAR",
    "Agent11.MemoryProperties.ISAInfo.ISA1.DefaultRoundingMode": "NEAR",
    "Agent11.MemoryProperties.ISAInfo.ISA1.Fastf16": "TRUE",
    "Agent11.MemoryProperties.ISAInfo.ISA1.WorkgroupMaxSize": "1024(0x400)",
    "Agent11.MemoryProperties.ISAInfo.ISA1.WorkgroupMaxSizeperDimension.x": "1024(0x400)",
    "Agent11.MemoryProperties.ISAInfo.ISA1.WorkgroupMaxSizeperDimension.y": "1024(0x400)",
    "Agent11.MemoryProperties.ISAInfo.ISA1.WorkgroupMaxSizeperDimension.z": "1024(0x400)",
    "Agent11.MemoryProperties.ISAInfo.ISA1.GridMaxSize": "4294967295(0xffffffff)",
    "Agent11.MemoryProperties.ISAInfo.ISA1.GridMaxSizeperDimension.x": "4294967295(0xffffffff)",
    "Agent11.MemoryProperties.ISAInfo.ISA1.GridMaxSizeperDimension.y": "4294967295(0xffffffff)",
    "Agent11.MemoryProperties.ISAInfo.ISA1.GridMaxSizeperDimension.z": "4294967295(0xffffffff)",
    "Agent11.MemoryProperties.ISAInfo.ISA1.FBarrierMaxSize": "32",
    "Agent12.Name": "gfx908",
    "Agent12.Uuid": "GPU-878e69f63e8901c4",
    "Agent12.MarketingName": "AMDInstinctMI100",
    "Agent12.VendorName": "AMD",
    "Agent12.Feature": "KERNEL_DISPATCH",
    "Agent12.Profile": "BASE_PROFILE",
    "Agent12.FloatRoundMode": "NEAR",
    "Agent12.MaxQueueNumber": "128(0x80)",
    "Agent12.QueueMinSize": "64(0x40)",
    "Agent12.QueueMaxSize": "131072(0x20000)",
    "Agent12.QueueType": "MULTI",
    "Agent12.Node": "11",
    "Agent12.DeviceType": "GPU",
    "Agent12.CacheInfo.L1": "16(0x10)KB",
    "Agent12.CacheInfo.L2": "8192(0x2000)KB",
    "Agent12.ChipID": "29580(0x738c)",
    "Agent12.ASICRevision": "2(0x2)",
    "Agent12.CachelineSize": "64(0x40)",
    "Agent12.MaxClockFreq.(MHz)": "1502",
    "Agent12.BDFID": "768",
    "Agent12.InternalNodeID": "11",
    "Agent12.ComputeUnit": "120",
    "Agent12.SIMDsperCU": "4",
    "Agent12.ShaderEngines": "8",
    "Agent12.ShaderArrs.perEng.": "1",
    "Agent12.WatchPtsonAddr.Ranges": "4",
    "Agent12.CoherentHostAccess": "FALSE",
    "Agent12.MemoryProperties.Features": "KERNEL_DISPATCH",
    "Agent12.MemoryProperties.FastF16Operation": "TRUE",
    "Agent12.MemoryProperties.WavefrontSize": "64(0x40)",
    "Agent12.MemoryProperties.WorkgroupMaxSize": "1024(0x400)",
    "Agent12.MemoryProperties.WorkgroupMaxSizeperDimension.x": "1024(0x400)",
    "Agent12.MemoryProperties.WorkgroupMaxSizeperDimension.y": "1024(0x400)",
    "Agent12.MemoryProperties.WorkgroupMaxSizeperDimension.z": "1024(0x400)",
    "Agent12.MemoryProperties.MaxWavesPerCU": "40(0x28)",
    "Agent12.MemoryProperties.MaxWork-itemPerCU": "2560(0xa00)",
    "Agent12.MemoryProperties.GridMaxSize": "4294967295(0xffffffff)",
    "Agent12.MemoryProperties.GridMaxSizeperDimension.x": "4294967295(0xffffffff)",
    "Agent12.MemoryProperties.GridMaxSizeperDimension.y": "4294967295(0xffffffff)",
    "Agent12.MemoryProperties.GridMaxSizeperDimension.z": "4294967295(0xffffffff)",
    "Agent12.MemoryProperties.Maxfbarriers/Workgrp": "32",
    "Agent12.MemoryProperties.PacketProcessoruCode:": "60",
    "Agent12.MemoryProperties.SDMAengineuCode:": "18",
    "Agent12.MemoryProperties.IOMMUSupport:": "None",
    "Agent12.MemoryProperties.PoolInfo.Pool1.Segment": "GLOBAL",
    "Agent12.MemoryProperties.PoolInfo.Pool1.FLAGS": "COARSEGRAINED",
    "Agent12.MemoryProperties.PoolInfo.Pool1.Size": "33538048(0x1ffc000)KB",
    "Agent12.MemoryProperties.PoolInfo.Pool1.Allocatable": "TRUE",
    "Agent12.MemoryProperties.PoolInfo.Pool1.AllocGranule": "4KB",
    "Agent12.MemoryProperties.PoolInfo.Pool1.AllocRecommendedGranule": "2048KB",
    "Agent12.MemoryProperties.PoolInfo.Pool1.AllocAlignment": "4KB",
    "Agent12.MemoryProperties.PoolInfo.Pool1.Accessiblebyall": "FALSE",
    "Agent12.MemoryProperties.PoolInfo.Pool2.Segment": "GLOBAL",
    "Agent12.MemoryProperties.PoolInfo.Pool2.FLAGS": "EXTENDEDFINEGRAINED",
    "Agent12.MemoryProperties.PoolInfo.Pool2.Size": "33538048(0x1ffc000)KB",
    "Agent12.MemoryProperties.PoolInfo.Pool2.Allocatable": "TRUE",
    "Agent12.MemoryProperties.PoolInfo.Pool2.AllocGranule": "4KB",
    "Agent12.MemoryProperties.PoolInfo.Pool2.AllocRecommendedGranule": "2048KB",
    "Agent12.MemoryProperties.PoolInfo.Pool2.AllocAlignment": "4KB",
    "Agent12.MemoryProperties.PoolInfo.Pool2.Accessiblebyall": "FALSE",
    "Agent12.MemoryProperties.PoolInfo.Pool3.Segment": "GROUP",
    "Agent12.MemoryProperties.PoolInfo.Pool3.Size": "64(0x40)KB",
    "Agent12.MemoryProperties.PoolInfo.Pool3.Allocatable": "FALSE",
    "Agent12.MemoryProperties.PoolInfo.Pool3.AllocGranule": "0KB",
    "Agent12.MemoryProperties.PoolInfo.Pool3.AllocRecommendedGranule": "0KB",
    "Agent12.MemoryProperties.PoolInfo.Pool3.AllocAlignment": "0KB",
    "Agent12.MemoryProperties.PoolInfo.Pool3.Accessiblebyall": "FALSE",
    "Agent12.MemoryProperties.ISAInfo.ISA1.Name:amdgcn-amd-amdhsa--gfx908:sramecc+": "xnack-",
    "Agent12.MemoryProperties.ISAInfo.ISA1.MachineModels": "HSA_MACHINE_MODEL_LARGE",
    "Agent12.MemoryProperties.ISAInfo.ISA1.Profiles": "HSA_PROFILE_BASE",
    "Agent12.MemoryProperties.ISAInfo.ISA1.DefaultRoundingMode": "NEAR",
    "Agent12.MemoryProperties.ISAInfo.ISA1.DefaultRoundingMode": "NEAR",
    "Agent12.MemoryProperties.ISAInfo.ISA1.Fastf16": "TRUE",
    "Agent12.MemoryProperties.ISAInfo.ISA1.WorkgroupMaxSize": "1024(0x400)",
    "Agent12.MemoryProperties.ISAInfo.ISA1.WorkgroupMaxSizeperDimension.x": "1024(0x400)",
    "Agent12.MemoryProperties.ISAInfo.ISA1.WorkgroupMaxSizeperDimension.y": "1024(0x400)",
    "Agent12.MemoryProperties.ISAInfo.ISA1.WorkgroupMaxSizeperDimension.z": "1024(0x400)",
    "Agent12.MemoryProperties.ISAInfo.ISA1.GridMaxSize": "4294967295(0xffffffff)",
    "Agent12.MemoryProperties.ISAInfo.ISA1.GridMaxSizeperDimension.x": "4294967295(0xffffffff)",
    "Agent12.MemoryProperties.ISAInfo.ISA1.GridMaxSizeperDimension.y": "4294967295(0xffffffff)",
    "Agent12.MemoryProperties.ISAInfo.ISA1.GridMaxSizeperDimension.z": "4294967295(0xffffffff)",
    "Agent12.MemoryProperties.ISAInfo.ISA1.FBarrierMaxSize": "32",
    "Agent13.Name": "gfx908",
    "Agent13.Uuid": "GPU-380a5b6c9979524a",
    "Agent13.MarketingName": "AMDInstinctMI100",
    "Agent13.VendorName": "AMD",
    "Agent13.Feature": "KERNEL_DISPATCH",
    "Agent13.Profile": "BASE_PROFILE",
    "Agent13.FloatRoundMode": "NEAR",
    "Agent13.MaxQueueNumber": "128(0x80)",
    "Agent13.QueueMinSize": "64(0x40)",
    "Agent13.QueueMaxSize": "131072(0x20000)",
    "Agent13.QueueType": "MULTI",
    "Agent13.Node": "12",
    "Agent13.DeviceType": "GPU",
    "Agent13.CacheInfo.L1": "16(0x10)KB",
    "Agent13.CacheInfo.L2": "8192(0x2000)KB",
    "Agent13.ChipID": "29580(0x738c)",
    "Agent13.ASICRevision": "2(0x2)",
    "Agent13.CachelineSize": "64(0x40)",
    "Agent13.MaxClockFreq.(MHz)": "1502",
    "Agent13.BDFID": "41728",
    "Agent13.InternalNodeID": "12",
    "Agent13.ComputeUnit": "120",
    "Agent13.SIMDsperCU": "4",
    "Agent13.ShaderEngines": "8",
    "Agent13.ShaderArrs.perEng.": "1",
    "Agent13.WatchPtsonAddr.Ranges": "4",
    "Agent13.CoherentHostAccess": "FALSE",
    "Agent13.MemoryProperties.Features": "KERNEL_DISPATCH",
    "Agent13.MemoryProperties.FastF16Operation": "TRUE",
    "Agent13.MemoryProperties.WavefrontSize": "64(0x40)",
    "Agent13.MemoryProperties.WorkgroupMaxSize": "1024(0x400)",
    "Agent13.MemoryProperties.WorkgroupMaxSizeperDimension.x": "1024(0x400)",
    "Agent13.MemoryProperties.WorkgroupMaxSizeperDimension.y": "1024(0x400)",
    "Agent13.MemoryProperties.WorkgroupMaxSizeperDimension.z": "1024(0x400)",
    "Agent13.MemoryProperties.MaxWavesPerCU": "40(0x28)",
    "Agent13.MemoryProperties.MaxWork-itemPerCU": "2560(0xa00)",
    "Agent13.MemoryProperties.GridMaxSize": "4294967295(0xffffffff)",
    "Agent13.MemoryProperties.GridMaxSizeperDimension.x": "4294967295(0xffffffff)",
    "Agent13.MemoryProperties.GridMaxSizeperDimension.y": "4294967295(0xffffffff)",
    "Agent13.MemoryProperties.GridMaxSizeperDimension.z": "4294967295(0xffffffff)",
    "Agent13.MemoryProperties.Maxfbarriers/Workgrp": "32",
    "Agent13.MemoryProperties.PacketProcessoruCode:": "60",
    "Agent13.MemoryProperties.SDMAengineuCode:": "18",
    "Agent13.MemoryProperties.IOMMUSupport:": "None",
    "Agent13.MemoryProperties.PoolInfo.Pool1.Segment": "GLOBAL",
    "Agent13.MemoryProperties.PoolInfo.Pool1.FLAGS": "COARSEGRAINED",
    "Agent13.MemoryProperties.PoolInfo.Pool1.Size": "33538048(0x1ffc000)KB",
    "Agent13.MemoryProperties.PoolInfo.Pool1.Allocatable": "TRUE",
    "Agent13.MemoryProperties.PoolInfo.Pool1.AllocGranule": "4KB",
    "Agent13.MemoryProperties.PoolInfo.Pool1.AllocRecommendedGranule": "2048KB",
    "Agent13.MemoryProperties.PoolInfo.Pool1.AllocAlignment": "4KB",
    "Agent13.MemoryProperties.PoolInfo.Pool1.Accessiblebyall": "FALSE",
    "Agent13.MemoryProperties.PoolInfo.Pool2.Segment": "GLOBAL",
    "Agent13.MemoryProperties.PoolInfo.Pool2.FLAGS": "EXTENDEDFINEGRAINED",
    "Agent13.MemoryProperties.PoolInfo.Pool2.Size": "33538048(0x1ffc000)KB",
    "Agent13.MemoryProperties.PoolInfo.Pool2.Allocatable": "TRUE",
    "Agent13.MemoryProperties.PoolInfo.Pool2.AllocGranule": "4KB",
    "Agent13.MemoryProperties.PoolInfo.Pool2.AllocRecommendedGranule": "2048KB",
    "Agent13.MemoryProperties.PoolInfo.Pool2.AllocAlignment": "4KB",
    "Agent13.MemoryProperties.PoolInfo.Pool2.Accessiblebyall": "FALSE",
    "Agent13.MemoryProperties.PoolInfo.Pool3.Segment": "GROUP",
    "Agent13.MemoryProperties.PoolInfo.Pool3.Size": "64(0x40)KB",
    "Agent13.MemoryProperties.PoolInfo.Pool3.Allocatable": "FALSE",
    "Agent13.MemoryProperties.PoolInfo.Pool3.AllocGranule": "0KB",
    "Agent13.MemoryProperties.PoolInfo.Pool3.AllocRecommendedGranule": "0KB",
    "Agent13.MemoryProperties.PoolInfo.Pool3.AllocAlignment": "0KB",
    "Agent13.MemoryProperties.PoolInfo.Pool3.Accessiblebyall": "FALSE",
    "Agent13.MemoryProperties.ISAInfo.ISA1.Name:amdgcn-amd-amdhsa--gfx908:sramecc+": "xnack-",
    "Agent13.MemoryProperties.ISAInfo.ISA1.MachineModels": "HSA_MACHINE_MODEL_LARGE",
    "Agent13.MemoryProperties.ISAInfo.ISA1.Profiles": "HSA_PROFILE_BASE",
    "Agent13.MemoryProperties.ISAInfo.ISA1.DefaultRoundingMode": "NEAR",
    "Agent13.MemoryProperties.ISAInfo.ISA1.DefaultRoundingMode": "NEAR",
    "Agent13.MemoryProperties.ISAInfo.ISA1.Fastf16": "TRUE",
    "Agent13.MemoryProperties.ISAInfo.ISA1.WorkgroupMaxSize": "1024(0x400)",
    "Agent13.MemoryProperties.ISAInfo.ISA1.WorkgroupMaxSizeperDimension.x": "1024(0x400)",
    "Agent13.MemoryProperties.ISAInfo.ISA1.WorkgroupMaxSizeperDimension.y": "1024(0x400)",
    "Agent13.MemoryProperties.ISAInfo.ISA1.WorkgroupMaxSizeperDimension.z": "1024(0x400)",
    "Agent13.MemoryProperties.ISAInfo.ISA1.GridMaxSize": "4294967295(0xffffffff)",
    "Agent13.MemoryProperties.ISAInfo.ISA1.GridMaxSizeperDimension.x": "4294967295(0xffffffff)",
    "Agent13.MemoryProperties.ISAInfo.ISA1.GridMaxSizeperDimension.y": "4294967295(0xffffffff)",
    "Agent13.MemoryProperties.ISAInfo.ISA1.GridMaxSizeperDimension.z": "4294967295(0xffffffff)",
    "Agent13.MemoryProperties.ISAInfo.ISA1.FBarrierMaxSize": "32",
    "Agent14.Name": "gfx908",
    "Agent14.Uuid": "GPU-abe51b8184405f91",
    "Agent14.MarketingName": "AMDInstinctMI100",
    "Agent14.VendorName": "AMD",
    "Agent14.Feature": "KERNEL_DISPATCH",
    "Agent14.Profile": "BASE_PROFILE",
    "Agent14.FloatRoundMode": "NEAR",
    "Agent14.MaxQueueNumber": "128(0x80)",
    "Agent14.QueueMinSize": "64(0x40)",
    "Agent14.QueueMaxSize": "131072(0x20000)",
    "Agent14.QueueType": "MULTI",
    "Agent14.Node": "13",
    "Agent14.DeviceType": "GPU",
    "Agent14.CacheInfo.L1": "16(0x10)KB",
    "Agent14.CacheInfo.L2": "8192(0x2000)KB",
    "Agent14.ChipID": "29580(0x738c)",
    "Agent14.ASICRevision": "2(0x2)",
    "Agent14.CachelineSize": "64(0x40)",
    "Agent14.MaxClockFreq.(MHz)": "1502",
    "Agent14.BDFID": "33536",
    "Agent14.InternalNodeID": "13",
    "Agent14.ComputeUnit": "120",
    "Agent14.SIMDsperCU": "4",
    "Agent14.ShaderEngines": "8",
    "Agent14.ShaderArrs.perEng.": "1",
    "Agent14.WatchPtsonAddr.Ranges": "4",
    "Agent14.CoherentHostAccess": "FALSE",
    "Agent14.MemoryProperties.Features": "KERNEL_DISPATCH",
    "Agent14.MemoryProperties.FastF16Operation": "TRUE",
    "Agent14.MemoryProperties.WavefrontSize": "64(0x40)",
    "Agent14.MemoryProperties.WorkgroupMaxSize": "1024(0x400)",
    "Agent14.MemoryProperties.WorkgroupMaxSizeperDimension.x": "1024(0x400)",
    "Agent14.MemoryProperties.WorkgroupMaxSizeperDimension.y": "1024(0x400)",
    "Agent14.MemoryProperties.WorkgroupMaxSizeperDimension.z": "1024(0x400)",
    "Agent14.MemoryProperties.MaxWavesPerCU": "40(0x28)",
    "Agent14.MemoryProperties.MaxWork-itemPerCU": "2560(0xa00)",
    "Agent14.MemoryProperties.GridMaxSize": "4294967295(0xffffffff)",
    "Agent14.MemoryProperties.GridMaxSizeperDimension.x": "4294967295(0xffffffff)",
    "Agent14.MemoryProperties.GridMaxSizeperDimension.y": "4294967295(0xffffffff)",
    "Agent14.MemoryProperties.GridMaxSizeperDimension.z": "4294967295(0xffffffff)",
    "Agent14.MemoryProperties.Maxfbarriers/Workgrp": "32",
    "Agent14.MemoryProperties.PacketProcessoruCode:": "60",
    "Agent14.MemoryProperties.SDMAengineuCode:": "18",
    "Agent14.MemoryProperties.IOMMUSupport:": "None",
    "Agent14.MemoryProperties.PoolInfo.Pool1.Segment": "GLOBAL",
    "Agent14.MemoryProperties.PoolInfo.Pool1.FLAGS": "COARSEGRAINED",
    "Agent14.MemoryProperties.PoolInfo.Pool1.Size": "33538048(0x1ffc000)KB",
    "Agent14.MemoryProperties.PoolInfo.Pool1.Allocatable": "TRUE",
    "Agent14.MemoryProperties.PoolInfo.Pool1.AllocGranule": "4KB",
    "Agent14.MemoryProperties.PoolInfo.Pool1.AllocRecommendedGranule": "2048KB",
    "Agent14.MemoryProperties.PoolInfo.Pool1.AllocAlignment": "4KB",
    "Agent14.MemoryProperties.PoolInfo.Pool1.Accessiblebyall": "FALSE",
    "Agent14.MemoryProperties.PoolInfo.Pool2.Segment": "GLOBAL",
    "Agent14.MemoryProperties.PoolInfo.Pool2.FLAGS": "EXTENDEDFINEGRAINED",
    "Agent14.MemoryProperties.PoolInfo.Pool2.Size": "33538048(0x1ffc000)KB",
    "Agent14.MemoryProperties.PoolInfo.Pool2.Allocatable": "TRUE",
    "Agent14.MemoryProperties.PoolInfo.Pool2.AllocGranule": "4KB",
    "Agent14.MemoryProperties.PoolInfo.Pool2.AllocRecommendedGranule": "2048KB",
    "Agent14.MemoryProperties.PoolInfo.Pool2.AllocAlignment": "4KB",
    "Agent14.MemoryProperties.PoolInfo.Pool2.Accessiblebyall": "FALSE",
    "Agent14.MemoryProperties.PoolInfo.Pool3.Segment": "GROUP",
    "Agent14.MemoryProperties.PoolInfo.Pool3.Size": "64(0x40)KB",
    "Agent14.MemoryProperties.PoolInfo.Pool3.Allocatable": "FALSE",
    "Agent14.MemoryProperties.PoolInfo.Pool3.AllocGranule": "0KB",
    "Agent14.MemoryProperties.PoolInfo.Pool3.AllocRecommendedGranule": "0KB",
    "Agent14.MemoryProperties.PoolInfo.Pool3.AllocAlignment": "0KB",
    "Agent14.MemoryProperties.PoolInfo.Pool3.Accessiblebyall": "FALSE",
    "Agent14.MemoryProperties.ISAInfo.ISA1.Name:amdgcn-amd-amdhsa--gfx908:sramecc+": "xnack-",
    "Agent14.MemoryProperties.ISAInfo.ISA1.MachineModels": "HSA_MACHINE_MODEL_LARGE",
    "Agent14.MemoryProperties.ISAInfo.ISA1.Profiles": "HSA_PROFILE_BASE",
    "Agent14.MemoryProperties.ISAInfo.ISA1.DefaultRoundingMode": "NEAR",
    "Agent14.MemoryProperties.ISAInfo.ISA1.DefaultRoundingMode": "NEAR",
    "Agent14.MemoryProperties.ISAInfo.ISA1.Fastf16": "TRUE",
    "Agent14.MemoryProperties.ISAInfo.ISA1.WorkgroupMaxSize": "1024(0x400)",
    "Agent14.MemoryProperties.ISAInfo.ISA1.WorkgroupMaxSizeperDimension.x": "1024(0x400)",
    "Agent14.MemoryProperties.ISAInfo.ISA1.WorkgroupMaxSizeperDimension.y": "1024(0x400)",
    "Agent14.MemoryProperties.ISAInfo.ISA1.WorkgroupMaxSizeperDimension.z": "1024(0x400)",
    "Agent14.MemoryProperties.ISAInfo.ISA1.GridMaxSize": "4294967295(0xffffffff)",
    "Agent14.MemoryProperties.ISAInfo.ISA1.GridMaxSizeperDimension.x": "4294967295(0xffffffff)",
    "Agent14.MemoryProperties.ISAInfo.ISA1.GridMaxSizeperDimension.y": "4294967295(0xffffffff)",
    "Agent14.MemoryProperties.ISAInfo.ISA1.GridMaxSizeperDimension.z": "4294967295(0xffffffff)",
    "Agent14.MemoryProperties.ISAInfo.ISA1.FBarrierMaxSize": "32"
  }
}